hissbytenotation/__init__.py
hissbytenotation/deserialize_by_import.py
hissbytenotation/dump_to_json.py
hissbytenotation/serialize_deserialize.py
hissbytenotation/supported_types.py
hissbytenotation-0.2.0.dist-info/LICENSE
hissbytenotation-0.2.0.dist-info/METADATA
hissbytenotation-0.2.0.dist-info/WHEEL
hissbytenotation-0.2.0.dist-info/RECORD
