Metadata-Version: 2.1
Name: hissbytenotation
Version: 0.2.0
Summary: Serialize and deserialize data to python source notation (hbn)
Home-page: https://github.com/matthewdeanmartin/hissbytenotation
License: MIT
Keywords: serializer,deserializer,hbn
Author: Matthew Martin
Author-email: matthewdeanmartin@gmail.com
Requires-Python: >=3.8
Classifier: Development Status :: 3 - Alpha
Classifier: Intended Audience :: Developers
Classifier: License :: OSI Approved :: MIT License
Classifier: Operating System :: OS Independent
Classifier: Programming Language :: Python
Classifier: Programming Language :: Python :: 3
Classifier: Programming Language :: Python :: 3.8
Classifier: Programming Language :: Python :: 3.9
Classifier: Programming Language :: Python :: 3.10
Classifier: Programming Language :: Python :: 3.11
Project-URL: Bug Tracker, https://github.com/matthewdeanmartin/hissbytenotation/issues
Project-URL: Change Log, https://github.com/matthewdeanmartin/hissbytenotation/blob/main/CHANGES.md
Project-URL: Documentation, https://github.com/matthewdeanmartin/hissbytenotation
Project-URL: Repository, https://github.com/matthewdeanmartin/hissbytenotation
